setup.py
drf_docs/__init__.py
drf_docs/api_docs.py
drf_docs/api_endpoint.py
drf_docs/settings.py
drf_docs/urls.py
drf_docs/views.py
drf_docs.egg-info/PKG-INFO
drf_docs.egg-info/SOURCES.txt
drf_docs.egg-info/dependency_links.txt
drf_docs.egg-info/requires.txt
drf_docs.egg-info/top_level.txt
drf_docs/static/drf_docs/css/style.css
drf_docs/static/drf_docs/fonts/FontAwesome.otf
drf_docs/static/drf_docs/fonts/fontawesome-webfont.eot
drf_docs/static/drf_docs/fonts/fontawesome-webfont.svg
drf_docs/static/drf_docs/fonts/fontawesome-webfont.ttf
drf_docs/static/drf_docs/fonts/fontawesome-webfont.woff
drf_docs/static/drf_docs/fonts/fontawesome-webfont.woff2
drf_docs/static/drf_docs/fonts/glyphicons-halflings-regular.eot
drf_docs/static/drf_docs/fonts/glyphicons-halflings-regular.svg
drf_docs/static/drf_docs/fonts/glyphicons-halflings-regular.ttf
drf_docs/static/drf_docs/fonts/glyphicons-halflings-regular.woff
drf_docs/static/drf_docs/fonts/glyphicons-halflings-regular.woff2
drf_docs/static/drf_docs/js/dist.min.js
drf_docs/static/drf_docs/less/style.less
drf_docs/templates/drf_docs/base.html
drf_docs/templates/drf_docs/docs.html
drf_docs/templates/drf_docs/home.html